[
	{
		"objectId": "6266C7A8-CCCB-498F-8E5C-FA613B7B5580",
		"kind": "text",
		"name": "viewThree",
		"originalName": "viewThree",
		"maskFrame": null,
		"layerFrame": {
			"x": 998,
			"y": 132,
			"width": 375,
			"height": 667
		},
		"visible": true,
		"metadata": {
			"string": "View 3",
			"css": [
				"/* View 3: */",
				"font-family: SFUIText-Regular;",
				"font-size: 40px;",
				"color: #FFFFFF;"
			]
		},
		"backgroundColor": "rgba(99, 42.2313179347826, 41, 1)",
		"image": {
			"path": "images/Layer-viewThree-nji2nkm3.png",
			"frame": {
				"x": 998,
				"y": 132,
				"width": 375,
				"height": 667
			}
		},
		"children": []
	},
	{
		"objectId": "4970EFBE-EE7A-487A-94E6-0B899A22252E",
		"kind": "text",
		"name": "viewTwo",
		"originalName": "viewTwo",
		"maskFrame": null,
		"layerFrame": {
			"x": 573,
			"y": 132,
			"width": 375,
			"height": 667
		},
		"visible": true,
		"metadata": {
			"string": "View 2",
			"css": [
				"/* View 2: */",
				"font-family: SFUIText-Regular;",
				"font-size: 40px;",
				"color: #FFFFFF;"
			]
		},
		"backgroundColor": "rgba(41, 99, 96.57676630434784, 1)",
		"image": {
			"path": "images/Layer-viewTwo-ndk3mevg.png",
			"frame": {
				"x": 573,
				"y": 132,
				"width": 375,
				"height": 667
			}
		},
		"children": []
	},
	{
		"objectId": "ABD5D9C0-D765-44DE-B5F9-7B42098A8D9E",
		"kind": "text",
		"name": "viewOne",
		"originalName": "viewOne",
		"maskFrame": null,
		"layerFrame": {
			"x": 148,
			"y": 132,
			"width": 375,
			"height": 667
		},
		"visible": true,
		"metadata": {
			"string": "View 1",
			"css": [
				"/* View 1: */",
				"font-family: SFUIText-Regular;",
				"font-size: 40px;",
				"color: #FFFFFF;"
			]
		},
		"backgroundColor": "rgba(47.00000000000003, 41, 99, 1)",
		"image": {
			"path": "images/Layer-viewOne-qujenuq5.png",
			"frame": {
				"x": 148,
				"y": 132,
				"width": 375,
				"height": 667
			}
		},
		"children": []
	}
]